mongoengine_todict/__init__.py
mongoengine_todict/errors.py
mongoengine_todict/mixin.py
tests/__init__.py
tests/test_mixin.py
mongoengine_todict-0.1.2.dist-info/LICENSE
mongoengine_todict-0.1.2.dist-info/METADATA
mongoengine_todict-0.1.2.dist-info/WHEEL
mongoengine_todict-0.1.2.dist-info/top_level.txt
mongoengine_todict-0.1.2.dist-info/RECORD
